main.v
module mux_4_to_1(
    output reg Y,
    input [3:0] X,
    input [1:0] select 
);
always @(X,select)
case(select)
2'b00: Y=X[0];
2'b01: Y=X[1];
2'b10: Y=X[2];
2'b11: Y=X[3];
endcase
endmodule

module de_mux_1_to_4(
    output reg [3:0] Y,
    input X,
    input [1:0] select 
);
always @(X,select)
case(select)
2'b00: begin Y[0]=X;{Y[1],Y[2],Y[3]}=3'b000; end
2'b01: begin Y[1]=X;{Y[0],Y[2],Y[3]}=3'b000; end
2'b10: begin Y[2]=X;{Y[1],Y[0],Y[3]}=3'b000; end
2'b11: begin Y[3]=X;{Y[1],Y[2],Y[0]}=3'b000; end
endcase
endmodule

module de_mux_1_to_4_rev(
    output reg [3:0] Y,
    input X,
    input [1:0] select 
);
always @(X,select)
case(select)
2'b00: begin Y[0]=(!X);{Y[1],Y[2],Y[3]}=3'b111; end
2'b01: begin Y[1]=(!X);{Y[0],Y[2],Y[3]}=3'b111; end
2'b10: begin Y[2]=(!X);{Y[1],Y[0],Y[3]}=3'b111; end
2'b11: begin Y[3]=(!X);{Y[1],Y[2],Y[0]}=3'b111; end
endcase
endmodule

module counter_60(
    output reg next,R,O,G,
    input T,clk,reset
);
reg [5:0] state;
always @(posedge clk,negedge reset)
if (reset==1'b0) begin state<=6'b000000; end
else begin
    if (state>=6'b000000 && state<6'b110110) begin
        if(T==1'b1) state<=state+6'b000001;
        else state<=6'b110110; end
    else if (state==6'b110110) state<=state+6'b000001;
    else if (state>=6'b110111 && state<=6'b111010) state<=state+6'b000001;
    else if (state>=6'b111011) state<=6'b000000;
end

always @(state)
if (state>=6'b000000 && state<=6'b110110) begin
    G=1'b1;R=1'b1;O=1'b0;next=1'b0;end
else if (state>=6'b110111 && state<=6'b111010)begin
    G=1'b0;R=1'b1;O=1'b1;next=1'b0;end
else if (state>=6'b111011)begin
    G=1'b0;R=1'b1;O=1'b1;next=1'b1;end
endmodule

module traffic_side(
    output reg [1:0] side,
    input next,t1,t2,t3,t4,clk,reset
);
always @(posedge clk,negedge reset)
if (reset==1'b0) side<=2'b00;
else 
case (side)
2'b00: if (next==1'b0) side<=2'b00;else begin
    if (t2==1'b1) side<=2'b01;
    else if (t3==1'b1) side<=2'b10;
    else if (t4==1'b1) side<=2'b11;
 end
2'b01: if (next==1'b0) side<=2'b01;else begin
    if (t3==1'b1) side<=2'b10;
    else if (t4==1'b1) side<=2'b11;
    else if (t1==1'b1) side<=2'b00;
 end
2'b10: if (next==1'b0) side<=2'b10;else begin
    if (t4==1'b1) side<=2'b11;
    else if (t1==1'b1) side<=2'b00;
    else if (t2==1'b1) side<=2'b01;
 end
2'b11: if (next==1'b0) side<=2'b11;else begin
    if (t1==1'b1) side<=2'b00;
    else if (t2==1'b1) side<=2'b01;
    else if (t3==1'b1) side<=2'b10;
 end
endcase
endmodule

module main_module(
    output R1,O1,G1,
    output R2,O2,G2,
    output R3,O3,G3,
    output R4,O4,G4,
    input t1,t2,t3,t4,clk,reset
);
wire [1:0] side;
wire next,R,G,O,T;

mux_4_to_1 M1(T,{t4,t3,t2,t1},side);
de_mux_1_to_4 D1({G4,G3,G2,G1},G,side);
de_mux_1_to_4 D2({O4,O3,O2,O1},O,side);
de_mux_1_to_4_rev V1({R4,R3,R2,R1},R,side);

traffic_side T1(side,next,t1,t2,t3,t4,clk,reset);
counter_60 C1(next,R,O,G,T,clk,reset);
endmodule

t_main.v
`timescale 100ms/1ms
`include "main.v"
module t_main;
wire R1,O1,G1;
wire R2,O2,G2;
wire R3,O3,G3;
wire R4,O4,G4;
reg t1,t2,t3,t4,clk,reset;

main_module Q1(R1,O1,G1,R2,O2,G2,R3,O3,G3,R4,O4,G4,t1,t2,t3,t4,clk,reset);

initial begin
    $dumpfile("dump.vcd");
    $dumpvars(0,t_main);
    clk=1'b0;
end
always #5 clk=(!clk);
initial #5000 $finish;

initial fork
t1=1'b1;
t2=1'b1;
t3=1'b1;
t4=1'b1;
reset = 1'b0;
#2 reset = 1'b1;
#200 t1=1'b0;
#2000 t4=1'b0;
#3000 t2=1'b0;
#3000 t3=1'b0;
#3600 t1=1'b1;
#4400 t3=1'b1;
join
endmodule

dump.vcd
$date
	Mon Dec 06 17:10:56 2021
$end
$version
	Icarus Verilog
$end
$timescale
	1ms
$end
$scope module t_main $end
$var wire 1 ! R4 $end
$var wire 1 " R3 $end
$var wire 1 # R2 $end
$var wire 1 $ R1 $end
$var wire 1 % O4 $end
$var wire 1 & O3 $end
$var wire 1 ' O2 $end
$var wire 1 ( O1 $end
$var wire 1 ) G4 $end
$var wire 1 * G3 $end
$var wire 1 + G2 $end
$var wire 1 , G1 $end
$var reg 1 - clk $end
$var reg 1 . reset $end
$var reg 1 / t1 $end
$var reg 1 0 t2 $end
$var reg 1 1 t3 $end
$var reg 1 2 t4 $end
$scope module Q1 $end
$var wire 1 - clk $end
$var wire 1 . reset $end
$var wire 1 / t1 $end
$var wire 1 0 t2 $end
$var wire 1 1 t3 $end
$var wire 1 2 t4 $end
$var wire 2 3 side [1:0] $end
$var wire 1 4 next $end
$var wire 1 5 T $end
$var wire 1 ! R4 $end
$var wire 1 " R3 $end
$var wire 1 # R2 $end
$var wire 1 $ R1 $end
$var wire 1 6 R $end
$var wire 1 % O4 $end
$var wire 1 & O3 $end
$var wire 1 ' O2 $end
$var wire 1 ( O1 $end
$var wire 1 7 O $end
$var wire 1 ) G4 $end
$var wire 1 * G3 $end
$var wire 1 + G2 $end
$var wire 1 , G1 $end
$var wire 1 8 G $end
$scope module C1 $end
$var wire 1 - clk $end
$var wire 1 . reset $end
$var wire 1 5 T $end
$var reg 1 8 G $end
$var reg 1 7 O $end
$var reg 1 6 R $end
$var reg 1 4 next $end
$var reg 6 9 state [5:0] $end
$upscope $end
$scope module D1 $end
$var wire 1 8 X $end
$var wire 2 : select [1:0] $end
$var reg 4 ; Y [3:0] $end
$upscope $end
$scope module D2 $end
$var wire 1 7 X $end
$var wire 2 < select [1:0] $end
$var reg 4 = Y [3:0] $end
$upscope $end
$scope module M1 $end
$var wire 4 > X [3:0] $end
$var wire 2 ? select [1:0] $end
$var reg 1 5 Y $end
$upscope $end
$scope module T1 $end
$var wire 1 - clk $end
$var wire 1 4 next $end
$var wire 1 . reset $end
$var wire 1 / t1 $end
$var wire 1 0 t2 $end
$var wire 1 1 t3 $end
$var wire 1 2 t4 $end
$var reg 2 @ side [1:0] $end
$upscope $end
$scope module V1 $end
$var wire 1 6 X $end
$var wire 2 A select [1:0] $end
$var reg 4 B Y [3:0] $end
$upscope $end
$upscope $end
$upscope $end
$enddefinitions $end
#0
$dumpvars
b1110 B
b0 A
b0 @
b0 ?
b1111 >
b0 =
b0 <
b1 ;
b0 :
b0 9
18
07
16
15
04
b0 3
12
11
10
1/
0.
0-
1,
0+
0*
0)
0(
0'
0&
0%
0$
1#
1"
1!
$end
#200
1.
#500
b1 9
1-
#1000
0-
#1500
b10 9
1-
#2000
0-
#2500
b11 9
1-
#3000
0-
#3500
b100 9
1-
#4000
0-
#4500
b101 9
1-
#5000
0-
#5500
b110 9
1-
#6000
0-
#6500
b111 9
1-
#7000
0-
#7500
b1000 9
1-
#8000
0-
#8500
b1001 9
1-
#9000
0-
#9500
b1010 9
1-
#10000
0-
#10500
b1011 9
1-
#11000
0-
#11500
b1100 9
1-
#12000
0-
#12500
b1101 9
1-
#13000
0-
#13500
b1110 9
1-
#14000
0-
#14500
b1111 9
1-
#15000
0-
#15500
b10000 9
1-
#16000
0-
#16500
b10001 9
1-
#17000
0-
#17500
b10010 9
1-
#18000
0-
#18500
b10011 9
1-
#19000
0-
#19500
b10100 9
1-
#20000
05
0-
b1110 >
0/
#20500
b110110 9
1-
#21000
0-
#21500
1(
0,
b1 =
b0 ;
17
08
b110111 9
1-
#22000
0-
#22500
b111000 9
1-
#23000
0-
#23500
b111001 9
1-
#24000
0-
#24500
b111010 9
1-
#25000
0-
#25500
14
b111011 9
1-
#26000
0-
#26500
1+
b10 ;
0(
0'
1$
0#
04
07
18
b0 =
15
b1101 B
b0 9
b1 3
b1 :
b1 <
b1 ?
b1 @
b1 A
1-
#27000
0-
#27500
b1 9
1-
#28000
0-
#28500
b10 9
1-
#29000
0-
#29500
b11 9
1-
#30000
0-
#30500
b100 9
1-
#31000
0-
#31500
b101 9
1-
#32000
0-
#32500
b110 9
1-
#33000
0-
#33500
b111 9
1-
#34000
0-
#34500
b1000 9
1-
#35000
0-
#35500
b1001 9
1-
#36000
0-
#36500
b1010 9
1-
#37000
0-
#37500
b1011 9
1-
#38000
0-
#38500
b1100 9
1-
#39000
0-
#39500
b1101 9
1-
#40000
0-
#40500
b1110 9
1-
#41000
0-
#41500
b1111 9
1-
#42000
0-
#42500
b10000 9
1-
#43000
0-
#43500
b10001 9
1-
#44000
0-
#44500
b10010 9
1-
#45000
0-
#45500
b10011 9
1-
#46000
0-
#46500
b10100 9
1-
#47000
0-
#47500
b10101 9
1-
#48000
0-
#48500
b10110 9
1-
#49000
0-
#49500
b10111 9
1-
#50000
0-
#50500
b11000 9
1-
#51000
0-
#51500
b11001 9
1-
#52000
0-
#52500
b11010 9
1-
#53000
0-
#53500
b11011 9
1-
#54000
0-
#54500
b11100 9
1-
#55000
0-
#55500
b11101 9
1-
#56000
0-
#56500
b11110 9
1-
#57000
0-
#57500
b11111 9
1-
#58000
0-
#58500
b100000 9
1-
#59000
0-
#59500
b100001 9
1-
#60000
0-
#60500
b100010 9
1-
#61000
0-
#61500
b100011 9
1-
#62000
0-
#62500
b100100 9
1-
#63000
0-
#63500
b100101 9
1-
#64000
0-
#64500
b100110 9
1-
#65000
0-
#65500
b100111 9
1-
#66000
0-
#66500
b101000 9
1-
#67000
0-
#67500
b101001 9
1-
#68000
0-
#68500
b101010 9
1-
#69000
0-
#69500
b101011 9
1-
#70000
0-
#70500
b101100 9
1-
#71000
0-
#71500
b101101 9
1-
#72000
0-
#72500
b101110 9
1-
#73000
0-
#73500
b101111 9
1-
#74000
0-
#74500
b110000 9
1-
#75000
0-
#75500
b110001 9
1-
#76000
0-
#76500
b110010 9
1-
#77000
0-
#77500
b110011 9
1-
#78000
0-
#78500
b110100 9
1-
#79000
0-
#79500
b110101 9
1-
#80000
0-
#80500
b110110 9
1-
#81000
0-
#81500
1'
0+
b10 =
b0 ;
17
08
b110111 9
1-
#82000
0-
#82500
b111000 9
1-
#83000
0-
#83500
b111001 9
1-
#84000
0-
#84500
b111010 9
1-
#85000
0-
#85500
14
b111011 9
1-
#86000
0-
#86500
1*
b100 ;
0'
0&
1#
0"
04
07
18
b0 =
b1011 B
b0 9
b10 3
b10 :
b10 <
b10 ?
b10 @
b10 A
1-
#87000
0-
#87500
b1 9
1-
#88000
0-
#88500
b10 9
1-
#89000
0-
#89500
b11 9
1-
#90000
0-
#90500
b100 9
1-
#91000
0-
#91500
b101 9
1-
#92000
0-
#92500
b110 9
1-
#93000
0-
#93500
b111 9
1-
#94000
0-
#94500
b1000 9
1-
#95000
0-
#95500
b1001 9
1-
#96000
0-
#96500
b1010 9
1-
#97000
0-
#97500
b1011 9
1-
#98000
0-
#98500
b1100 9
1-
#99000
0-
#99500
b1101 9
1-
#100000
0-
#100500
b1110 9
1-
#101000
0-
#101500
b1111 9
1-
#102000
0-
#102500
b10000 9
1-
#103000
0-
#103500
b10001 9
1-
#104000
0-
#104500
b10010 9
1-
#105000
0-
#105500
b10011 9
1-
#106000
0-
#106500
b10100 9
1-
#107000
0-
#107500
b10101 9
1-
#108000
0-
#108500
b10110 9
1-
#109000
0-
#109500
b10111 9
1-
#110000
0-
#110500
b11000 9
1-
#111000
0-
#111500
b11001 9
1-
#112000
0-
#112500
b11010 9
1-
#113000
0-
#113500
b11011 9
1-
#114000
0-
#114500
b11100 9
1-
#115000
0-
#115500
b11101 9
1-
#116000
0-
#116500
b11110 9
1-
#117000
0-
#117500
b11111 9
1-
#118000
0-
#118500
b100000 9
1-
#119000
0-
#119500
b100001 9
1-
#120000
0-
#120500
b100010 9
1-
#121000
0-
#121500
b100011 9
1-
#122000
0-
#122500
b100100 9
1-
#123000
0-
#123500
b100101 9
1-
#124000
0-
#124500
b100110 9
1-
#125000
0-
#125500
b100111 9
1-
#126000
0-
#126500
b101000 9
1-
#127000
0-
#127500
b101001 9
1-
#128000
0-
#128500
b101010 9
1-
#129000
0-
#129500
b101011 9
1-
#130000
0-
#130500
b101100 9
1-
#131000
0-
#131500
b101101 9
1-
#132000
0-
#132500
b101110 9
1-
#133000
0-
#133500
b101111 9
1-
#134000
0-
#134500
b110000 9
1-
#135000
0-
#135500
b110001 9
1-
#136000
0-
#136500
b110010 9
1-
#137000
0-
#137500
b110011 9
1-
#138000
0-
#138500
b110100 9
1-
#139000
0-
#139500
b110101 9
1-
#140000
0-
#140500
b110110 9
1-
#141000
0-
#141500
1&
0*
b100 =
b0 ;
17
08
b110111 9
1-
#142000
0-
#142500
b111000 9
1-
#143000
0-
#143500
b111001 9
1-
#144000
0-
#144500
b111010 9
1-
#145000
0-
#145500
14
b111011 9
1-
#146000
0-
#146500
1)
b1000 ;
0&
0%
1"
0!
04
07
18
b0 =
b111 B
b0 9
b11 3
b11 :
b11 <
b11 ?
b11 @
b11 A
1-
#147000
0-
#147500
b1 9
1-
#148000
0-
#148500
b10 9
1-
#149000
0-
#149500
b11 9
1-
#150000
0-
#150500
b100 9
1-
#151000
0-
#151500
b101 9
1-
#152000
0-
#152500
b110 9
1-
#153000
0-
#153500
b111 9
1-
#154000
0-
#154500
b1000 9
1-
#155000
0-
#155500
b1001 9
1-
#156000
0-
#156500
b1010 9
1-
#157000
0-
#157500
b1011 9
1-
#158000
0-
#158500
b1100 9
1-
#159000
0-
#159500
b1101 9
1-
#160000
0-
#160500
b1110 9
1-
#161000
0-
#161500
b1111 9
1-
#162000
0-
#162500
b10000 9
1-
#163000
0-
#163500
b10001 9
1-
#164000
0-
#164500
b10010 9
1-
#165000
0-
#165500
b10011 9
1-
#166000
0-
#166500
b10100 9
1-
#167000
0-
#167500
b10101 9
1-
#168000
0-
#168500
b10110 9
1-
#169000
0-
#169500
b10111 9
1-
#170000
0-
#170500
b11000 9
1-
#171000
0-
#171500
b11001 9
1-
#172000
0-
#172500
b11010 9
1-
#173000
0-
#173500
b11011 9
1-
#174000
0-
#174500
b11100 9
1-
#175000
0-
#175500
b11101 9
1-
#176000
0-
#176500
b11110 9
1-
#177000
0-
#177500
b11111 9
1-
#178000
0-
#178500
b100000 9
1-
#179000
0-
#179500
b100001 9
1-
#180000
0-
#180500
b100010 9
1-
#181000
0-
#181500
b100011 9
1-
#182000
0-
#182500
b100100 9
1-
#183000
0-
#183500
b100101 9
1-
#184000
0-
#184500
b100110 9
1-
#185000
0-
#185500
b100111 9
1-
#186000
0-
#186500
b101000 9
1-
#187000
0-
#187500
b101001 9
1-
#188000
0-
#188500
b101010 9
1-
#189000
0-
#189500
b101011 9
1-
#190000
0-
#190500
b101100 9
1-
#191000
0-
#191500
b101101 9
1-
#192000
0-
#192500
b101110 9
1-
#193000
0-
#193500
b101111 9
1-
#194000
0-
#194500
b110000 9
1-
#195000
0-
#195500
b110001 9
1-
#196000
0-
#196500
b110010 9
1-
#197000
0-
#197500
b110011 9
1-
#198000
0-
#198500
b110100 9
1-
#199000
0-
#199500
b110101 9
1-
#200000
05
0-
b110 >
02
#200500
b110110 9
1-
#201000
0-
#201500
1%
0)
b1000 =
b0 ;
17
08
b110111 9
1-
#202000
0-
#202500
b111000 9
1-
#203000
0-
#203500
b111001 9
1-
#204000
0-
#204500
b111010 9
1-
#205000
0-
#205500
14
b111011 9
1-
#206000
0-
#206500
1+
b10 ;
0%
0'
1!
0#
04
07
18
b0 =
15
b1101 B
b0 9
b1 3
b1 :
b1 <
b1 ?
b1 @
b1 A
1-
#207000
0-
#207500
b1 9
1-
#208000
0-
#208500
b10 9
1-
#209000
0-
#209500
b11 9
1-
#210000
0-
#210500
b100 9
1-
#211000
0-
#211500
b101 9
1-
#212000
0-
#212500
b110 9
1-
#213000
0-
#213500
b111 9
1-
#214000
0-
#214500
b1000 9
1-
#215000
0-
#215500
b1001 9
1-
#216000
0-
#216500
b1010 9
1-
#217000
0-
#217500
b1011 9
1-
#218000
0-
#218500
b1100 9
1-
#219000
0-
#219500
b1101 9
1-
#220000
0-
#220500
b1110 9
1-
#221000
0-
#221500
b1111 9
1-
#222000
0-
#222500
b10000 9
1-
#223000
0-
#223500
b10001 9
1-
#224000
0-
#224500
b10010 9
1-
#225000
0-
#225500
b10011 9
1-
#226000
0-
#226500
b10100 9
1-
#227000
0-
#227500
b10101 9
1-
#228000
0-
#228500
b10110 9
1-
#229000
0-
#229500
b10111 9
1-
#230000
0-
#230500
b11000 9
1-
#231000
0-
#231500
b11001 9
1-
#232000
0-
#232500
b11010 9
1-
#233000
0-
#233500
b11011 9
1-
#234000
0-
#234500
b11100 9
1-
#235000
0-
#235500
b11101 9
1-
#236000
0-
#236500
b11110 9
1-
#237000
0-
#237500
b11111 9
1-
#238000
0-
#238500
b100000 9
1-
#239000
0-
#239500
b100001 9
1-
#240000
0-
#240500
b100010 9
1-
#241000
0-
#241500
b100011 9
1-
#242000
0-
#242500
b100100 9
1-
#243000
0-
#243500
b100101 9
1-
#244000
0-
#244500
b100110 9
1-
#245000
0-
#245500
b100111 9
1-
#246000
0-
#246500
b101000 9
1-
#247000
0-
#247500
b101001 9
1-
#248000
0-
#248500
b101010 9
1-
#249000
0-
#249500
b101011 9
1-
#250000
0-
#250500
b101100 9
1-
#251000
0-
#251500
b101101 9
1-
#252000
0-
#252500
b101110 9
1-
#253000
0-
#253500
b101111 9
1-
#254000
0-
#254500
b110000 9
1-
#255000
0-
#255500
b110001 9
1-
#256000
0-
#256500
b110010 9
1-
#257000
0-
#257500
b110011 9
1-
#258000
0-
#258500
b110100 9
1-
#259000
0-
#259500
b110101 9
1-
#260000
0-
#260500
b110110 9
1-
#261000
0-
#261500
1'
0+
b10 =
b0 ;
17
08
b110111 9
1-
#262000
0-
#262500
b111000 9
1-
#263000
0-
#263500
b111001 9
1-
#264000
0-
#264500
b111010 9
1-
#265000
0-
#265500
14
b111011 9
1-
#266000
0-
#266500
1*
b100 ;
0'
0&
1#
0"
04
07
18
b0 =
b1011 B
b0 9
b10 3
b10 :
b10 <
b10 ?
b10 @
b10 A
1-
#267000
0-
#267500
b1 9
1-
#268000
0-
#268500
b10 9
1-
#269000
0-
#269500
b11 9
1-
#270000
0-
#270500
b100 9
1-
#271000
0-
#271500
b101 9
1-
#272000
0-
#272500
b110 9
1-
#273000
0-
#273500
b111 9
1-
#274000
0-
#274500
b1000 9
1-
#275000
0-
#275500
b1001 9
1-
#276000
0-
#276500
b1010 9
1-
#277000
0-
#277500
b1011 9
1-
#278000
0-
#278500
b1100 9
1-
#279000
0-
#279500
b1101 9
1-
#280000
0-
#280500
b1110 9
1-
#281000
0-
#281500
b1111 9
1-
#282000
0-
#282500
b10000 9
1-
#283000
0-
#283500
b10001 9
1-
#284000
0-
#284500
b10010 9
1-
#285000
0-
#285500
b10011 9
1-
#286000
0-
#286500
b10100 9
1-
#287000
0-
#287500
b10101 9
1-
#288000
0-
#288500
b10110 9
1-
#289000
0-
#289500
b10111 9
1-
#290000
0-
#290500
b11000 9
1-
#291000
0-
#291500
b11001 9
1-
#292000
0-
#292500
b11010 9
1-
#293000
0-
#293500
b11011 9
1-
#294000
0-
#294500
b11100 9
1-
#295000
0-
#295500
b11101 9
1-
#296000
0-
#296500
b11110 9
1-
#297000
0-
#297500
b11111 9
1-
#298000
0-
#298500
b100000 9
1-
#299000
0-
#299500
b100001 9
1-
#300000
05
0-
00
b0 >
01
#300500
b110110 9
1-
#301000
0-
#301500
1&
0*
b100 =
b0 ;
17
08
b110111 9
1-
#302000
0-
#302500
b111000 9
1-
#303000
0-
#303500
b111001 9
1-
#304000
0-
#304500
b111010 9
1-
#305000
0-
#305500
14
b111011 9
1-
#306000
0-
#306500
0&
1*
b0 =
b100 ;
04
07
18
b0 9
1-
#307000
0-
#307500
b110110 9
1-
#308000
0-
#308500
1&
0*
b100 =
b0 ;
17
08
b110111 9
1-
#309000
0-
#309500
b111000 9
1-
#310000
0-
#310500
b111001 9
1-
#311000
0-
#311500
b111010 9
1-
#312000
0-
#312500
14
b111011 9
1-
#313000
0-
#313500
0&
1*
b0 =
b100 ;
04
07
18
b0 9
1-
#314000
0-
#314500
b110110 9
1-
#315000
0-
#315500
1&
0*
b100 =
b0 ;
17
08
b110111 9
1-
#316000
0-
#316500
b111000 9
1-
#317000
0-
#317500
b111001 9
1-
#318000
0-
#318500
b111010 9
1-
#319000
0-
#319500
14
b111011 9
1-
#320000
0-
#320500
0&
1*
b0 =
b100 ;
04
07
18
b0 9
1-
#321000
0-
#321500
b110110 9
1-
#322000
0-
#322500
1&
0*
b100 =
b0 ;
17
08
b110111 9
1-
#323000
0-
#323500
b111000 9
1-
#324000
0-
#324500
b111001 9
1-
#325000
0-
#325500
b111010 9
1-
#326000
0-
#326500
14
b111011 9
1-
#327000
0-
#327500
0&
1*
b0 =
b100 ;
04
07
18
b0 9
1-
#328000
0-
#328500
b110110 9
1-
#329000
0-
#329500
1&
0*
b100 =
b0 ;
17
08
b110111 9
1-
#330000
0-
#330500
b111000 9
1-
#331000
0-
#331500
b111001 9
1-
#332000
0-
#332500
b111010 9
1-
#333000
0-
#333500
14
b111011 9
1-
#334000
0-
#334500
0&
1*
b0 =
b100 ;
04
07
18
b0 9
1-
#335000
0-
#335500
b110110 9
1-
#336000
0-
#336500
1&
0*
b100 =
b0 ;
17
08
b110111 9
1-
#337000
0-
#337500
b111000 9
1-
#338000
0-
#338500
b111001 9
1-
#339000
0-
#339500
b111010 9
1-
#340000
0-
#340500
14
b111011 9
1-
#341000
0-
#341500
0&
1*
b0 =
b100 ;
04
07
18
b0 9
1-
#342000
0-
#342500
b110110 9
1-
#343000
0-
#343500
1&
0*
b100 =
b0 ;
17
08
b110111 9
1-
#344000
0-
#344500
b111000 9
1-
#345000
0-
#345500
b111001 9
1-
#346000
0-
#346500
b111010 9
1-
#347000
0-
#347500
14
b111011 9
1-
#348000
0-
#348500
0&
1*
b0 =
b100 ;
04
07
18
b0 9
1-
#349000
0-
#349500
b110110 9
1-
#350000
0-
#350500
1&
0*
b100 =
b0 ;
17
08
b110111 9
1-
#351000
0-
#351500
b111000 9
1-
#352000
0-
#352500
b111001 9
1-
#353000
0-
#353500
b111010 9
1-
#354000
0-
#354500
14
b111011 9
1-
#355000
0-
#355500
0&
1*
b0 =
b100 ;
04
07
18
b0 9
1-
#356000
0-
#356500
b110110 9
1-
#357000
0-
#357500
1&
0*
b100 =
b0 ;
17
08
b110111 9
1-
#358000
0-
#358500
b111000 9
1-
#359000
0-
#359500
b111001 9
1-
#360000
0-
b1 >
1/
#360500
b111010 9
1-
#361000
0-
#361500
14
b111011 9
1-
#362000
0-
#362500
1,
b1 ;
0&
0(
1"
0$
04
07
18
b0 =
15
b1110 B
b0 9
b0 3
b0 :
b0 <
b0 ?
b0 @
b0 A
1-
#363000
0-
#363500
b1 9
1-
#364000
0-
#364500
b10 9
1-
#365000
0-
#365500
b11 9
1-
#366000
0-
#366500
b100 9
1-
#367000
0-
#367500
b101 9
1-
#368000
0-
#368500
b110 9
1-
#369000
0-
#369500
b111 9
1-
#370000
0-
#370500
b1000 9
1-
#371000
0-
#371500
b1001 9
1-
#372000
0-
#372500
b1010 9
1-
#373000
0-
#373500
b1011 9
1-
#374000
0-
#374500
b1100 9
1-
#375000
0-
#375500
b1101 9
1-
#376000
0-
#376500
b1110 9
1-
#377000
0-
#377500
b1111 9
1-
#378000
0-
#378500
b10000 9
1-
#379000
0-
#379500
b10001 9
1-
#380000
0-
#380500
b10010 9
1-
#381000
0-
#381500
b10011 9
1-
#382000
0-
#382500
b10100 9
1-
#383000
0-
#383500
b10101 9
1-
#384000
0-
#384500
b10110 9
1-
#385000
0-
#385500
b10111 9
1-
#386000
0-
#386500
b11000 9
1-
#387000
0-
#387500
b11001 9
1-
#388000
0-
#388500
b11010 9
1-
#389000
0-
#389500
b11011 9
1-
#390000
0-
#390500
b11100 9
1-
#391000
0-
#391500
b11101 9
1-
#392000
0-
#392500
b11110 9
1-
#393000
0-
#393500
b11111 9
1-
#394000
0-
#394500
b100000 9
1-
#395000
0-
#395500
b100001 9
1-
#396000
0-
#396500
b100010 9
1-
#397000
0-
#397500
b100011 9
1-
#398000
0-
#398500
b100100 9
1-
#399000
0-
#399500
b100101 9
1-
#400000
0-
#400500
b100110 9
1-
#401000
0-
#401500
b100111 9
1-
#402000
0-
#402500
b101000 9
1-
#403000
0-
#403500
b101001 9
1-
#404000
0-
#404500
b101010 9
1-
#405000
0-
#405500
b101011 9
1-
#406000
0-
#406500
b101100 9
1-
#407000
0-
#407500
b101101 9
1-
#408000
0-
#408500
b101110 9
1-
#409000
0-
#409500
b101111 9
1-
#410000
0-
#410500
b110000 9
1-
#411000
0-
#411500
b110001 9
1-
#412000
0-
#412500
b110010 9
1-
#413000
0-
#413500
b110011 9
1-
#414000
0-
#414500
b110100 9
1-
#415000
0-
#415500
b110101 9
1-
#416000
0-
#416500
b110110 9
1-
#417000
0-
#417500
1(
0,
b1 =
b0 ;
17
08
b110111 9
1-
#418000
0-
#418500
b111000 9
1-
#419000
0-
#419500
b111001 9
1-
#420000
0-
#420500
b111010 9
1-
#421000
0-
#421500
14
b111011 9
1-
#422000
0-
#422500
0(
1,
b0 =
b1 ;
04
07
18
b0 9
1-
#423000
0-
#423500
b1 9
1-
#424000
0-
#424500
b10 9
1-
#425000
0-
#425500
b11 9
1-
#426000
0-
#426500
b100 9
1-
#427000
0-
#427500
b101 9
1-
#428000
0-
#428500
b110 9
1-
#429000
0-
#429500
b111 9
1-
#430000
0-
#430500
b1000 9
1-
#431000
0-
#431500
b1001 9
1-
#432000
0-
#432500
b1010 9
1-
#433000
0-
#433500
b1011 9
1-
#434000
0-
#434500
b1100 9
1-
#435000
0-
#435500
b1101 9
1-
#436000
0-
#436500
b1110 9
1-
#437000
0-
#437500
b1111 9
1-
#438000
0-
#438500
b10000 9
1-
#439000
0-
#439500
b10001 9
1-
#440000
0-
b101 >
11
#440500
b10010 9
1-
#441000
0-
#441500
b10011 9
1-
#442000
0-
#442500
b10100 9
1-
#443000
0-
#443500
b10101 9
1-
#444000
0-
#444500
b10110 9
1-
#445000
0-
#445500
b10111 9
1-
#446000
0-
#446500
b11000 9
1-
#447000
0-
#447500
b11001 9
1-
#448000
0-
#448500
b11010 9
1-
#449000
0-
#449500
b11011 9
1-
#450000
0-
#450500
b11100 9
1-
#451000
0-
#451500
b11101 9
1-
#452000
0-
#452500
b11110 9
1-
#453000
0-
#453500
b11111 9
1-
#454000
0-
#454500
b100000 9
1-
#455000
0-
#455500
b100001 9
1-
#456000
0-
#456500
b100010 9
1-
#457000
0-
#457500
b100011 9
1-
#458000
0-
#458500
b100100 9
1-
#459000
0-
#459500
b100101 9
1-
#460000
0-
#460500
b100110 9
1-
#461000
0-
#461500
b100111 9
1-
#462000
0-
#462500
b101000 9
1-
#463000
0-
#463500
b101001 9
1-
#464000
0-
#464500
b101010 9
1-
#465000
0-
#465500
b101011 9
1-
#466000
0-
#466500
b101100 9
1-
#467000
0-
#467500
b101101 9
1-
#468000
0-
#468500
b101110 9
1-
#469000
0-
#469500
b101111 9
1-
#470000
0-
#470500
b110000 9
1-
#471000
0-
#471500
b110001 9
1-
#472000
0-
#472500
b110010 9
1-
#473000
0-
#473500
b110011 9
1-
#474000
0-
#474500
b110100 9
1-
#475000
0-
#475500
b110101 9
1-
#476000
0-
#476500
b110110 9
1-
#477000
0-
#477500
1(
0,
b1 =
b0 ;
17
08
b110111 9
1-
#478000
0-
#478500
b111000 9
1-
#479000
0-
#479500
b111001 9
1-
#480000
0-
#480500
b111010 9
1-
#481000
0-
#481500
14
b111011 9
1-
#482000
0-
#482500
1*
b100 ;
0(
0&
1$
0"
04
07
18
b0 =
b1011 B
b0 9
b10 3
b10 :
b10 <
b10 ?
b10 @
b10 A
1-
#483000
0-
#483500
b1 9
1-
#484000
0-
#484500
b10 9
1-
#485000
0-
#485500
b11 9
1-
#486000
0-
#486500
b100 9
1-
#487000
0-
#487500
b101 9
1-
#488000
0-
#488500
b110 9
1-
#489000
0-
#489500
b111 9
1-
#490000
0-
#490500
b1000 9
1-
#491000
0-
#491500
b1001 9
1-
#492000
0-
#492500
b1010 9
1-
#493000
0-
#493500
b1011 9
1-
#494000
0-
#494500
b1100 9
1-
#495000
0-
#495500
b1101 9
1-
#496000
0-
#496500
b1110 9
1-
#497000
0-
#497500
b1111 9
1-
#498000
0-
#498500
b10000 9
1-
#499000
0-
#499500
b10001 9
1-
